yatc/__init__.py
yatc-0.1.0.dist-info/METADATA
yatc-0.1.0.dist-info/WHEEL
yatc-0.1.0.dist-info/RECORD
